LICENSE
README.md
pyproject.toml
setup.py
mpdscrobble/__init__.py
mpdscrobble/__main__.py
mpdscrobble/constants.py
mpdscrobble/mpdscrobble.py
mpdscrobble/utils.py
mpdscrobble.egg-info/PKG-INFO
mpdscrobble.egg-info/SOURCES.txt
mpdscrobble.egg-info/dependency_links.txt
mpdscrobble.egg-info/entry_points.txt
mpdscrobble.egg-info/requires.txt
mpdscrobble.egg-info/top_level.txt
tests/__init__.py
tests/conftest.py
tests/test_mpdscrobble_lastfm.py
tests/test_mpdscrobble_listenbrainz.py
tests/test_mpdscrobble_maloja.py
tests/test_mpdscrobble_track.py