Metadata-Version: 2.1
Name: mpdscrobble
Version: 0.3.4
Summary: A simple Last.fm scrobbler for MPD.
Home-page: https://github.com/dbeley/mpdscrobble
Author: dbeley
Author-email: dbeley@protonmail.com
Classifier: Programming Language :: Python :: 3
Classifier: Operating System :: POSIX :: Linux
License-File: LICENSE
Requires-Dist: httpx
Requires-Dist: python-mpd2
Requires-Dist: pylast
